{"$schema":"https://json-schema.org/draft/2020-12/schema","$id":"contracts/schemas/idempotency-record.schema.json","title":"FlowiseAI PM Idempotency Record Contract","type":"object","required":["idempotency_key","schema_version","operation_name","request_hash","task_id","created_at","status","outcome_ref","runtime_claim"],"properties":{"idempotency_key":{"type":"string","minLength":1},"schema_version":{"type":"string","minLength":1},"operation_name":{"type":"string","enum":["create_task","transition_task_state","claim_next_task","renew_task_lease","release_task_lease","persist_handoff","persist_role_output","append_audit_event"]},"request_hash":{"type":"string","minLength":1},"task_id":{"type":"string","minLength":1},"created_at":{"type":"string","minLength":1},"completed_at":{"type":["string","null"]},"status":{"type":"string","enum":["started","succeeded","failed","replayed"]},"outcome_ref":{"type":"object","additionalProperties":true},"runtime_claim":{"type":"boolean","const":false}},"additionalProperties":false}
